tap_amplitude/__init__.py
tap_amplitude/schemas/event.json
tap_amplitude_api-0.1.8.dist-info/LICENSE
tap_amplitude_api-0.1.8.dist-info/METADATA
tap_amplitude_api-0.1.8.dist-info/WHEEL
tap_amplitude_api-0.1.8.dist-info/entry_points.txt
tap_amplitude_api-0.1.8.dist-info/top_level.txt
tap_amplitude_api-0.1.8.dist-info/RECORD
